DCD/lab3/vending_machine.v
`timescale 1ns / 1ps

// 自动售货机控制器 - 最终可综合版（适配原XDC约束）
// 修复所有关键警告，可顺利生成比特流
module vending_machine(  // 恢复原模块名，匹配XDC
    input wire clk,                      // 恢复原端口名，匹配XDC
    input wire [2:0] product_selected,   // 恢复原端口名，匹配XDC
    input wire button_5,                 // 恢复原端口名，匹配XDC
    input wire button_2,                 // 恢复原端口名，匹配XDC
    input wire button_1,                 // 恢复原端口名，匹配XDC
    input wire button_05,                // 恢复原端口名，匹配XDC
    output wire [6:0] A2G,               // 恢复原端口名，匹配XDC
    output reg [7:0] AN,                 // 恢复原端口名，匹配XDC
    output reg DP,                       // 恢复原端口名，匹配XDC
    output reg success_led               // 恢复原端口名，匹配XDC
);

// ====================== 1. 价格表（可综合版）======================
reg [7:0] prod_price;         
always @(*) begin
    case(product_selected)
        3'd0: prod_price = 8'd0;    // 无效商品
        3'd1: prod_price = 8'd5;    // 1号: 0.5元 (5*0.1)
        3'd2: prod_price = 8'd10;   // 2号: 1元 (10*0.1)
        3'd3: prod_price = 8'd15;   // 3号: 1.5元 (15*0.1)
        3'd4: prod_price = 8'd20;   // 4号: 2元 (20*0.1)
        3'd5: prod_price = 8'd65;   // 5号: 6.5元 (65*0.1)
        3'd6: prod_price = 8'd130;  // 6号: 13元 (130*0.1)
        3'd7: prod_price = 8'd0;    // 无效商品
    endcase
end

// ====================== 2. 核心状态变量 =======================
reg [7:0] current_price = 8'd0;     // 显式初始化
reg [7:0] total_paid = 8'd0;        // 显式初始化
reg [2:0] last_switch = 3'b000;
reg [3:0] display_value = 4'd0;     // 显式初始化

// ====================== 3. 消抖时钟生成（50MHz→3Hz）======================
reg [23:0] count = 24'd0;
reg clk2 = 1'b0;

always @(posedge clk) begin
    count <= count + 1'b1;
    if (count[23] == 1'b1) begin
        clk2 <= ~clk2;
        count <= 24'd0;
    end
end

// ====================== 4. 按钮消抖+边沿检测 =======================
reg button_5_reg1=0, button_5_reg2=0; // 显式初始化
reg button_2_reg1=0, button_2_reg2=0;
reg button_1_reg1=0, button_1_reg2=0;
reg button_05_reg1=0, button_05_reg2=0;

wire button_5_edge;
wire button_2_edge;
wire button_1_edge;
wire button_05_edge;

// 双寄存器同步消抖
always @(posedge clk2) begin
    button_5_reg1 <= button_5;
    button_2_reg1 <= button_2;
    button_1_reg1 <= button_1;
    button_05_reg1 <= button_05;
    
    button_5_reg2 <= button_5_reg1;
    button_2_reg2 <= button_2_reg1;
    button_1_reg2 <= button_1_reg1;
    button_05_reg2 <= button_05_reg1;
end

// 上升沿检测（避免组合逻辑冒险）
assign button_5_edge = button_5_reg1 & ~button_5_reg2;
assign button_2_edge = button_2_reg1 & ~button_2_reg2;
assign button_1_edge = button_1_reg1 & ~button_1_reg2;
assign button_05_edge = button_05_reg1 & ~button_05_reg2;

// ====================== 5. 商品选择+投币逻辑 =======================
always @(posedge clk2) begin
    if (product_selected != last_switch) begin
        last_switch <= product_selected;
        current_price <= prod_price;
        total_paid <= 8'd0;
        success_led <= 1'b0;
    end else begin
        // 投币累加（避免多条件同时触发）
        if (button_5_edge) begin
            total_paid <= total_paid + 8'd50;  // 5元=50*0.1
        end else if (button_2_edge) begin
            total_paid <= total_paid + 8'd20;  // 2元=20*0.1
        end else if (button_1_edge) begin
            total_paid <= total_paid + 8'd10;  // 1元=10*0.1
        end else if (button_05_edge) begin
            total_paid <= total_paid + 8'd5;   // 0.5元=5*0.1
        end

        // 交易成功判断（避免逻辑歧义）
        success_led <= (total_paid >= current_price) && (current_price > 8'd0);
    end
end

// ====================== 6. 数码管扫描驱动 =======================
reg [19:0] scan_counter = 20'd0;    // 显式初始化
wire [1:0] scan_pos;

// 扫描时钟分频（100Hz）
always @(posedge clk) begin
    scan_counter <= scan_counter + 1'b1;
    if (scan_counter == 20'd999_999) begin
        scan_counter <= 20'd0;
    end
end

assign scan_pos = scan_counter[18:17];

// 数码管译码逻辑（共阳极，匹配硬件）
reg [6:0] seg_output = 7'b1111111;  // 显式初始化
always @(*) begin
    case (display_value)
        4'd0: seg_output = 7'b1000000;
        4'd1: seg_output = 7'b1111001;
        4'd2: seg_output = 7'b0100100;
        4'd3: seg_output = 7'b0110000;
        4'd4: seg_output = 7'b0011001;
        4'd5: seg_output = 7'b0010010;
        4'd6: seg_output = 7'b0000010;
        4'd7: seg_output = 7'b1111000;
        4'd8: seg_output = 7'b0000000;
        4'd9: seg_output = 7'b0010000;
        default: seg_output = 7'b1111111;
    endcase
end
assign A2G = seg_output;

// 数码管动态扫描（消除悬空信号警告）
always @(*) begin
    AN = 8'b11111111;  // 默认值，消除警告
    DP = 1'b1;         // 默认值，消除警告
    display_value = 4'd0; // 默认值，消除警告
    
    case (scan_pos)
        2'b00: begin
            AN = 8'b11111110;
            DP = 1'b1;
            display_value = product_selected;
        end
        2'b01: begin
            AN = 8'b11111101;
            DP = 1'b1;
            display_value = total_paid % 10;
        end
        2'b10: begin
            AN = 8'b11111011;
            DP = 1'b0;
            display_value = (total_paid / 10) % 10;
        end
        2'b11: begin
            AN = 8'b11110111;
            DP = 1'b1;
            display_value = (total_paid / 100) % 10;
        end
    endcase
end

endmodule

DCD/lab3/project_1/project_1.srcs/sim_1/new/tb_vending_machine.v
// 修复版自动售货机Testbench
`timescale 1ns / 1ps

module tb_vending_machine;

reg clk;                  
reg [2:0] product_selected; 
reg button_5;             
reg button_2;             
reg button_1;             
reg button_05;            

wire [6:0] A2G;           
wire [7:0] AN;            
wire DP;                  
wire success_led;         

vending_machine uut (
    .clk(clk),
    .product_selected(product_selected),
    .button_5(button_5),
    .button_2(button_2),
    .button_1(button_1),
    .button_05(button_05),
    .A2G(A2G),
    .AN(AN),
    .DP(DP),
    .success_led(success_led)
);

// 100MHz时钟
initial begin
    clk = 0;
    forever #5 clk = ~clk; 
end

// 测试激励（适配3Hz消抖时钟）
initial begin
    product_selected = 3'b000;
    button_5 = 0;
    button_2 = 0;
    button_1 = 0;
    button_05 = 0;
    
    #1000;
    
    // 测试1号商品（0.5元）
    $display("=== 测试场景1：选择1号商品（0.5元） ===");
    product_selected = 3'b001; 
    #35000000; // 等待35ms（超过3Hz消抖周期）
    
    // 模拟按键抖动后按下
    button_05 = 1;
    #10000;    // 模拟10us抖动
    button_05 = 0;
    #10000;
    button_05 = 1;
    #40000000; // 稳定按下40ms
    button_05 = 0;
    #35000000; 
    
    if (success_led == 1) begin
        $display("场景1测试通过：成功LED点亮");
    end else begin
        $display("场景1测试失败：成功LED未点亮");
    end
    
    // 测试5号商品（6.5元）
    $display("\n=== 测试场景2：选择5号商品（6.5元） ===");
    product_selected = 3'b101; 
    #35000000; 
    
    button_5 = 1;
    #40000000;
    button_5 = 0;
    #35000000;
    
    button_1 = 1;
    #40000000;
    button_1 = 0;
    #35000000;
    
    button_05 = 1;
    #40000000;
    button_05 = 0;
    #35000000;
    
    if (success_led == 1) begin
        $display("场景2测试通过：成功LED点亮");
    end else begin
        $display("场景2测试失败：成功LED未点亮");
    end
    
    #100000000;
    $display("\n=== 所有测试场景执行完毕 ===");
    $finish;
end

initial begin
    $dumpfile("vending_machine_fixed.vcd");
    $dumpvars(0, tb_vending_machine);
end

endmodule

DCD/lab3/project_1/project_1.sim/sim_1/behav/xsim/vending_machine_fixed.vcd
$date
   Sun Dec  7 22:47:27 2025
$end

$version
  2024.1
  $dumpfile ("vending_machine_fixed.vcd") 
$end

$timescale
  1ps
$end

$scope module tb_vending_machine $end
$var reg 1 ! clk $end
$var reg 3 " product_selected [2:0] $end
$var reg 1 # button_5 $end
$var reg 1 $ button_2 $end
$var reg 1 % button_1 $end
$var reg 1 & button_05 $end
$var wire 7 ' A2G [6:0] $end
$var wire 8 ( AN [7:0] $end
$var wire 1 ) DP $end
$var wire 1 * success_led $end
$scope module uut $end
$var wire 1 + clk $end
$var wire 3 , product_selected [2:0] $end
$var wire 1 - button_5 $end
$var wire 1 . button_2 $end
$var wire 1 / button_1 $end
$var wire 1 0 button_05 $end
$var wire 7 ' A2G [6:0] $end
$var reg 8 1 AN [7:0] $end
$var reg 1 2 DP $end
$var reg 1 3 success_led $end
$var reg 8 4 prod_price [7:0] $end
$var reg 8 5 current_price [7:0] $end
$var reg 8 6 total_paid [7:0] $end
$var reg 3 7 last_switch [2:0] $end
$var reg 4 8 display_value [3:0] $end
$var reg 24 9 count [23:0] $end
$var reg 1 : clk2 $end
$var reg 1 ; button_5_reg1 $end
$var reg 1 < button_5_reg2 $end
$var reg 1 = button_2_reg1 $end
$var reg 1 > button_2_reg2 $end
$var reg 1 ? button_1_reg1 $end
$var reg 1 @ button_1_reg2 $end
$var reg 1 A button_05_reg1 $end
$var reg 1 B button_05_reg2 $end
$var wire 1 C button_5_edge $end
$var wire 1 D button_2_edge $end
$var wire 1 E button_1_edge $end
$var wire 1 F button_05_edge $end
$var reg 20 G scan_counter [19:0] $end
$var wire 2 H scan_pos [1:0] $end
$var reg 7 I seg_output [6:0] $end
$upscope $end
$upscope $end
$enddefinitions $end

#0
$dumpvars
0!
b0 "
0#
0$
0%
0&
b1000000 '
b11111110 (
1)
x*
0+
b0 ,
0-
0.
0/
00
b11111110 1
12
x3
b0 4
b0 5
b0 6
b0 7
b0 8
b0 9
0:
0;
0<
0=
0>
0?
0@
0A
0B
0C
0D
0E
0F
b0 G
b0 H
b1000000 I
$end

#5000
1!
1+
b1 9
b1 G

#10000
0!
0+

#15000
1!
1+
b10 9
b10 G

#20000
0!
0+

#25000
1!
1+
b11 9
b11 G

#30000
0!
0+

#35000
1!
1+
b100 9
b100 G

#40000
0!
0+

#45000
1!
1+
b101 9
b101 G

#50000
0!
0+

#55000
1!
1+
b110 9
b110 G

#60000
0!
0+

#65000
1!
1+
b111 9
b111 G

#70000
0!
0+

#75000
1!
1+
b1000 9
b1000 G

#80000
0!
0+

#85000
1!
1+
b1001 9
b1001 G

#90000
0!
0+

#95000
1!
1+
b1010 9
b1010 G

#100000
0!
0+

#105000
1!
1+
b1011 9
b1011 G

#110000
0!
0+

#115000
1!
1+
b1100 9
b1100 G

#120000
0!
0+

#125000
1!
1+
b1101 9
b1101 G

#130000
0!
0+

#135000
1!
1+
b1110 9
b1110 G

#140000
0!
0+

#145000
1!
1+
b1111 9
b1111 G

#150000
0!
0+

#155000
1!
1+
b10000 9
b10000 G

#160000
0!
0+

#165000
1!
1+
b10001 9
b10001 G

#170000
0!
0+

#175000
1!
1+
b10010 9
b10010 G

#180000
0!
0+

#185000
1!
1+
b10011 9
b10011 G

#190000
0!
0+

#195000
1!
1+
b10100 9
b10100 G

#200000
0!
0+

#205000
1!
1+
b10101 9
b10101 G

#210000
0!
0+

#215000
1!
1+
b10110 9
b10110 G

#220000
0!
0+

#225000
1!
1+
b10111 9
b10111 G

#230000
0!
0+

#235000
1!
1+
b11000 9
b11000 G

#240000
0!
0+

#245000
1!
1+
b11001 9
b11001 G

#250000
0!
0+

#255000
1!
1+
b11010 9
b11010 G

#260000
0!
0+

#265000
1!
1+
b11011 9
b11011 G

#270000
0!
0+

#275000
1!
1+
b11100 9
b11100 G

#280000
0!
0+

#285000
1!
1+
b11101 9
b11101 G

#290000
0!
0+

#295000
1!
1+
b11110 9
b11110 G

#300000
0!
0+

#305000
1!
1+
b11111 9
b11111 G

#310000
0!
0+

#315000
1!
1+
b100000 9
b100000 G

#320000
0!
0+

#325000
1!
1+
b100001 9
b100001 G

#330000
0!
0+

#335000
1!
1+
b100010 9
b100010 G

#340000
0!
0+

#345000
1!
1+
b100011 9
b100011 G

#350000
0!
0+

#355000
1!
1+
b100100 9
b100100 G

#360000
0!
0+

#365000
1!
1+
b100101 9
b100101 G

#370000
0!
0+

#375000
1!
1+
b100110 9
b100110 G

#380000
0!
0+

#385000
1!
1+
b100111 9
b100111 G

#390000
0!
0+

#395000
1!
1+
b101000 9
b101000 G

#400000
0!
0+

#405000
1!
1+
b101001 9
b101001 G

#410000
0!
0+

#415000
1!
1+
b101010 9
b101010 G

#420000
0!
0+

#425000
1!
1+
b101011 9
b101011 G

#430000
0!
0+

#435000
1!
1+
b101100 9
b101100 G

#440000
0!
0+

#445000
1!
1+
b101101 9
b101101 G

#450000
0!
0+

#455000
1!
1+
b101110 9
b101110 G

#460000
0!
0+

#465000
1!
1+
b101111 9
b101111 G

#470000
0!
0+

#475000
1!
1+
b110000 9
b110000 G

#480000
0!
0+

#485000
1!
1+
b110001 9
b110001 G

#490000
0!
0+

#495000
1!
1+
b110010 9
b110010 G

#500000
0!
0+

#505000
1!
1+
b110011 9
b110011 G

#510000
0!
0+

#515000
1!
1+
b110100 9
b110100 G

#520000
0!
0+

#525000
1!
1+
b110101 9
b110101 G

#530000
0!
0+

#535000
1!
1+
b110110 9
b110110 G

#540000
0!
0+

#545000
1!
1+
b110111 9
b110111 G

#550000
0!
0+

#555000
1!
1+
b111000 9
b111000 G

#560000
0!
0+

#565000
1!
1+
b111001 9
b111001 G

#570000
0!
0+

#575000
1!
1+
b111010 9
b111010 G

#580000
0!
0+

#585000
1!
1+
b111011 9
b111011 G

#590000
0!
0+

#595000
1!
1+
b111100 9
b111100 G

#600000
0!
0+

#605000
1!
1+
b111101 9
b111101 G

#610000
0!
0+

#615000
1!
1+
b111110 9
b111110 G

#620000
0!
0+

#625000
1!
1+
b111111 9
b111111 G

#630000
0!
0+

#635000
1!
1+
b1000000 9
b1000000 G

#640000
0!
0+

#645000
1!
1+
b1000001 9
b1000001 G

#650000
0!
0+

#655000
1!
1+
b1000010 9
b1000010 G

#660000
0!
0+

#665000
1!
1+
b1000011 9
b1000011 G

#670000
0!
0+

#675000
1!
1+
b1000100 9
b1000100 G

#680000
0!
0+

#685000
1!
1+
b1000101 9
b1000101 G

#690000
0!
0+

#695000
1!
1+
b1000110 9
b1000110 G

#700000
0!
0+

#705000
1!
1+
b1000111 9
b1000111 G

#710000
0!
0+

#715000
1!
1+
b1001000 9
b1001000 G

#720000
0!
0+

#725000
1!
1+
b1001001 9
b1001001 G

#730000
0!
0+

#735000
1!
1+
b1001010 9
b1001010 G

#740000
0!
0+

#745000
1!
1+
b1001011 9
b1001011 G

#750000
0!
0+

#755000
1!
1+
b1001100 9
b1001100 G

#760000
0!
0+

#765000
1!
1+
b1001101 9
b1001101 G

#770000
0!
0+

#775000
1!
1+
b1001110 9
b1001110 G

#780000
0!
0+

#785000
1!
1+
b1001111 9
b1001111 G

#790000
0!
0+

#795000
1!
1+
b1010000 9
b1010000 G

#800000
0!
0+

#805000
1!
1+
b1010001 9
b1010001 G

#810000
0!
0+

#815000
1!
1+
b1010010 9
b1010010 G

#820000
0!
0+

#825000
1!
1+
b1010011 9
b1010011 G

#830000
0!
0+

#835000
1!
1+
b1010100 9
b1010100 G

#840000
0!
0+

#845000
1!
1+
b1010101 9
b1010101 G

#850000
0!
0+

#855000
1!
1+
b1010110 9
b1010110 G

#860000
0!
0+

#865000
1!
1+
b1010111 9
b1010111 G

#870000
0!
0+

#875000
1!
1+
b1011000 9
b1011000 G

#880000
0!
0+

#885000
1!
1+
b1011001 9
b1011001 G

#890000
0!
0+

#895000
1!
1+
b1011010 9
b1011010 G

#900000
0!
0+

#905000
1!
1+
b1011011 9
b1011011 G

#910000
0!
0+

#915000
1!
1+
b1011100 9
b1011100 G

#920000
0!
0+

#925000
1!
1+
b1011101 9
b1011101 G

#930000
0!
0+

#935000
1!
1+
b1011110 9
b1011110 G

#940000
0!
0+

#945000
1!
1+
b1011111 9
b1011111 G

#950000
0!
0+

#955000
1!
1+
b1100000 9
b1100000 G

#960000
0!
0+

#965000
1!
1+
b1100001 9
b1100001 G

#970000
0!
0+

#975000
1!
1+
b1100010 9
b1100010 G

#980000
0!
0+

#985000
1!
1+
b1100011 9
b1100011 G

#990000
0!
0+

#995000
1!
1+
b1100100 9
b1100100 G

#1000000
0!
b1 "
b1111001 '
0+
b1 ,
b11111110 1
b101 4
b1 8
b1111001 I
